LICENSE
MANIFEST.in
README.rst
setup.py
adminlte_full/__init__.py
adminlte_full/admin.py
adminlte_full/apps.py
adminlte_full/assets.py
adminlte_full/menu.py
adminlte_full/messages.py
adminlte_full/models.py
adminlte_full/notifications.py
adminlte_full/tasks.py
adminlte_full/tests.py
adminlte_full/urls.py
adminlte_full/utils.py
adminlte_full/views.py
adminlte_full/__pycache__/__init__.cpython-35.pyc
adminlte_full/__pycache__/admin.cpython-35.pyc
adminlte_full/__pycache__/assets.cpython-35.pyc
adminlte_full/__pycache__/menu.cpython-35.pyc
adminlte_full/__pycache__/messages.cpython-35.pyc
adminlte_full/__pycache__/models.cpython-35.pyc
adminlte_full/__pycache__/notifications.cpython-35.pyc
adminlte_full/__pycache__/tasks.cpython-35.pyc
adminlte_full/__pycache__/urls.cpython-35.pyc
adminlte_full/__pycache__/utils.cpython-35.pyc
adminlte_full/__pycache__/views.cpython-35.pyc
adminlte_full/migrations/__init__.py
adminlte_full/migrations/__init__.pyc
adminlte_full/migrations/__pycache__/__init__.cpython-35.pyc
adminlte_full/static/adminlte-full.css
adminlte_full/static/AdminLTE/.git
adminlte_full/static/AdminLTE/.gitignore
adminlte_full/static/AdminLTE/.jshintrc
adminlte_full/static/AdminLTE/Gruntfile.js
adminlte_full/static/AdminLTE/LICENSE
adminlte_full/static/AdminLTE/README.md
adminlte_full/static/AdminLTE/bower.json
adminlte_full/static/AdminLTE/changelog
adminlte_full/static/AdminLTE/composer.json
adminlte_full/static/AdminLTE/index.html
adminlte_full/static/AdminLTE/index2.html
adminlte_full/static/AdminLTE/package.json
adminlte_full/static/AdminLTE/starter.html
adminlte_full/static/AdminLTE/bootstrap/css/bootstrap.css
adminlte_full/static/AdminLTE/bootstrap/css/bootstrap.css.map
adminlte_full/static/AdminLTE/bootstrap/css/bootstrap.min.css
adminlte_full/static/AdminLTE/bootstrap/css/bootstrap.min.css.map
adminlte_full/static/AdminLTE/bootstrap/fonts/glyphicons-halflings-regular.eot
adminlte_full/static/AdminLTE/bootstrap/fonts/glyphicons-halflings-regular.svg
django_adminlte_full.egg-info/PKG-INFO
django_adminlte_full.egg-info/SOURCES.txt
django_adminlte_full.egg-info/dependency_links.txt
django_adminlte_full.egg-info/requires.txt
django_adminlte_full.egg-info/top_level.txt
