Metadata-Version: 1.1
Name: django-adminlte-full
Version: 0.1.0
Summary: This Django application is port the AdminLTE Template for easy integration into Django Framework
Home-page: https://github.com/kyzima-spb/django-adminlte-full
Author: Kirill Vercetti
Author-email: office@kyzima-spb.com
License: Apache License 2.0
Platform: UNKNOWN
Classifier: Environment :: Web Environment
Classifier: Framework :: Django
Classifier: Intended Audience :: Developers
Classifier: License :: OSI Approved :: Apache Software License
Classifier: Operating System :: OS Independent
Classifier: Programming Language :: Python
Classifier: Topic :: Internet :: WWW/HTTP
Classifier: Topic :: Internet :: WWW/HTTP :: Dynamic Content
